apiresponsehandler.py
apiresponsehandler-0.0.1.dist-info/LICENSE.txt
apiresponsehandler-0.0.1.dist-info/METADATA
apiresponsehandler-0.0.1.dist-info/WHEEL
apiresponsehandler-0.0.1.dist-info/top_level.txt
apiresponsehandler-0.0.1.dist-info/RECORD
